MANIFEST.in
setup.py
Topsis_102103178.egg-info/PKG-INFO
Topsis_102103178.egg-info/SOURCES.txt
Topsis_102103178.egg-info/dependency_links.txt
Topsis_102103178.egg-info/entry_points.txt
Topsis_102103178.egg-info/requires.txt
Topsis_102103178.egg-info/top_level.txt
tests/__init__.py
tests/tests_topsis.py
topsis/__init__.py
topsis/topsis.py