Metadata-Version: 2.1
Name: Topsis-102103178
Version: 0.2.0
Classifier: Programming Language :: Python :: 3
Requires-Dist: pandas
Requires-Dist: numpy
